[
  {
    "id": "korean_hard_1_1",
    "subject": "korean",
    "question": "국어 문제 3-1-1",
    "options": ["정답", "오답1", "오답2", "오답3"],
    "correctIndex": 0,
    "explanation": "설명",
    "difficulty": 3
  },
  {
    "id": "korean_hard_1_2",
    "subject": "korean",
    "question": "국어 문제 3-1-2",
    "options": ["정답", "오답1", "오답2", "오답3"],
    "correctIndex": 0,
    "explanation": "설명",
    "difficulty": 3
  },
  {
    "id": "korean_hard_1_3",
    "subject": "korean",
    "question": "국어 문제 3-1-3",
    "options": ["정답", "오답1", "오답2", "오답3"],
    "correctIndex": 0,
    "explanation": "설명",
    "difficulty": 3
  },
  {
    "id": "korean_hard_1_4",
    "subject": "korean",
    "question": "국어 문제 3-1-4",
    "options": ["정답", "오답1", "오답2", "오답3"],
    "correctIndex": 0,
    "explanation": "설명",
    "difficulty": 3
  },
  {
    "id": "korean_hard_1_5",
    "subject": "korean",
    "question": "국어 문제 3-1-5",
    "options": ["정답", "오답1", "오답2", "오답3"],
    "correctIndex": 0,
    "explanation": "설명",
    "difficulty": 3
  }
]